[{"children":[{"dateAdded":1574683127859,"id":"1138","index":0,"parentId":"1","title":"百度","url":"https://www.baidu.com/"},{"children":[{"dateAdded":1574683127881,"id":"1155","index":0,"parentId":"1139","title":"鸠摩搜索","url":"https://www.jiumodiary.com/"},{"dateAdded":1574683127901,"id":"1156","index":1,"parentId":"1139","title":"down - 资源下载,计算机PDF下载","url":"https://www.jqhtml.com/down/"},{"dateAdded":1574938683865,"id":"1273","index":2,"parentId":"1139","title":"SoBooks - 优质的kindle电子书资源免费下载网站（原\"SoKindle\"）","url":"https://sobooks.cc/"},{"dateAdded":1574938763257,"id":"1274","index":3,"parentId":"1139","title":"虫部落-让搜索更简单！","url":"https://www.chongbuluo.com/"}],"dateAdded":1574683127861,"dateGroupModified":1574938763257,"id":"1139","index":1,"parentId":"1","title":"搜索"},{"children":[{"dateAdded":1574683127901,"id":"1157","index":0,"parentId":"1140","title":"网易邮箱","url":"https://mail.163.com/js6/main.jsp?sid=RDpoAvZSLxddTTHDXYSSBaoqgCPqaNpf&df=unknow#module=mbox.ListModule%7C%7B%22fid%22%3A1%2C%22order%22%3A%22date%22%2C%22desc%22%3Atrue%7D"}],"dateAdded":1574683127861,"dateGroupModified":1574683127901,"id":"1140","index":2,"parentId":"1","title":"邮箱"},{"children":[{"dateAdded":1574683127901,"id":"1158","index":0,"parentId":"1141","title":"YouTube","url":"https://www.youtube.com/"},{"dateAdded":1574683127901,"id":"1159","index":1,"parentId":"1141","title":"Android的ss客户端 · 科学上网相关知识总结","url":"https://crifan.github.io/scientific_network_summary/website/server_client_mode/ss_client/client_android.html"},{"dateAdded":1574683127902,"id":"1160","index":2,"parentId":"1141","title":"IPv6 test - IPv6/4 connectivity and speed test","url":"http://ipv6-test.com/"}],"dateAdded":1574683127862,"dateGroupModified":1574683127902,"id":"1141","index":3,"parentId":"1","title":"墙外"},{"children":[{"dateAdded":1574683127902,"id":"1161","index":0,"parentId":"1142","title":"教务处","url":"http://jwc.seu.edu.cn/"},{"dateAdded":1574683127902,"id":"1162","index":1,"parentId":"1142","title":"统一身份认证平台","url":"https://newids.seu.edu.cn/authserver/login?goto=http://my.seu.edu.cn/index.portal"},{"dateAdded":1574683127902,"id":"1163","index":2,"parentId":"1142","title":"统一身份认证","url":"http://202.119.25.2/"},{"dateAdded":1574683127902,"id":"1164","index":3,"parentId":"1142","title":"东南大学图书馆","url":"http://lib.seu.edu.cn/"},{"dateAdded":1574683127902,"id":"1165","index":4,"parentId":"1142","title":"东南大学自动化学院","url":"http://automation.seu.edu.cn/"},{"dateAdded":1574683127903,"id":"1166","index":5,"parentId":"1142","title":"东南大学电子邮件系统","url":"http://mail.seu.edu.cn/"},{"dateAdded":1574683127903,"id":"1167","index":6,"parentId":"1142","title":"东南大学-网络服务认证登录","url":"http://w.seu.edu.cn/"},{"dateAdded":1574683127903,"id":"1168","index":7,"parentId":"1142","title":"研究生院","url":"http://seugs.seu.edu.cn/"},{"dateAdded":1574683127903,"id":"1169","index":8,"parentId":"1142","title":"MATLAB正版化","url":"http://nic.seu.edu.cn/wwwwwwzbh/list.htm"},{"dateAdded":1574683127903,"id":"1170","index":9,"parentId":"1142","title":"网络与信息中心","url":"http://nic.seu.edu.cn/"}],"dateAdded":1574683127862,"dateGroupModified":1574683127903,"id":"1142","index":4,"parentId":"1","title":"东南大学"},{"children":[{"dateAdded":1574683127903,"id":"1171","index":0,"parentId":"1143","title":"英雄联盟_英雄联盟直播_网游竞技视频解说攻略_斗鱼 - 每个人的直播平台","url":"https://www.douyu.com/directory/game/LOL"},{"dateAdded":1574683127903,"id":"1172","index":1,"parentId":"1143","title":"英雄联盟直播_英雄联盟直播专区_LOL直播-虎牙直播","url":"https://www.huya.com/g/lol"},{"dateAdded":1574683127904,"id":"1173","index":2,"parentId":"1143","title":"英雄联盟 腾讯游戏官方直播平台 企鹅电竞","url":"https://egame.qq.com/livelist?layoutid=lol"},{"dateAdded":1574683127904,"id":"1174","index":3,"parentId":"1143","title":"League of Legends - Twitch","url":"https://www.twitch.tv/directory/game/League%20of%20Legends"},{"dateAdded":1574683127904,"id":"1175","index":4,"parentId":"1143","title":"哔哩哔哩 (゜-゜)つロ 干杯~-bilibili","url":"https://www.bilibili.com/"},{"dateAdded":1574683127904,"id":"1176","index":5,"parentId":"1143","title":"BT磁力搜索网站","url":"https://blog.csdn.net/roslei/article/details/70196145"},{"dateAdded":1574683127904,"id":"1177","index":6,"parentId":"1143","title":"最新电影在线播放,迅雷电影下载-影视大全","url":"http://www.yingshidaquan.cc/vod-show-id-1-p-1.html"},{"dateAdded":1574683127904,"id":"1178","index":7,"parentId":"1143","title":"电影 / 最新电影_电影天堂-迅雷电影下载","url":"https://www.dy2018.com/html/gndy/dyzz/index.html"},{"dateAdded":1574683127905,"id":"1179","index":8,"parentId":"1143","title":"影视大全 -无广告在线云点播 -迅雷电影下载","url":"http://tv699.com/"},{"dateAdded":1574683127905,"id":"1180","index":9,"parentId":"1143","title":"腾讯视频 - 中国领先的在线视频媒体平台,海量高清视频在线观看","url":"https://v.qq.com/"}],"dateAdded":1574683127863,"dateGroupModified":1574683127905,"id":"1143","index":5,"parentId":"1","title":"直播"},{"children":[{"dateAdded":1574683127905,"id":"1181","index":0,"parentId":"1144","title":"GitHub 教程","url":"https://blog.csdn.net/qq_35246620/article/details/66973794?tdsourcetag=s_pctim_aiomsg"},{"dateAdded":1574683127905,"id":"1182","index":1,"parentId":"1144","title":"Git处理 github 上传超过 100MB 文件","url":"http://www.liuxiao.org/2017/02/git-%E5%A4%84%E7%90%86-github-%E4%B8%8D%E5%85%81%E8%AE%B8%E4%B8%8A%E4%BC%A0%E8%B6%85%E8%BF%87-100mb-%E6%96%87%E4%BB%B6%E7%9A%84%E9%97%AE%E9%A2%98/"},{"dateAdded":1574683127905,"id":"1183","index":2,"parentId":"1144","title":"文档整体解决方案(readthedocs、github 、sphinx)使用 - youxin - 博客园","url":"https://www.cnblogs.com/youxin/p/3594161.html?tdsourcetag=s_pctim_aiomsg"},{"dateAdded":1574683127905,"id":"1184","index":3,"parentId":"1144","title":"使用sphinx记笔记 — sdut-jwch 0.1 documentation","url":"http://jwch.sdut.edu.cn/book/tool/UseSphinx.html"},{"dateAdded":1574683127905,"id":"1185","index":4,"parentId":"1144","title":"Sphinx-doc编写文档 - CSDN博客","url":"https://blog.csdn.net/weishantc/article/details/46729103?tdsourcetag=s_pctim_aiomsg"},{"dateAdded":1574683127906,"id":"1186","index":5,"parentId":"1144","title":"有哪些较好的壁纸网站？ - 知乎","url":"https://www.zhihu.com/question/32762402"},{"dateAdded":1574683127906,"id":"1187","index":6,"parentId":"1144","title":"如何安装向日葵远程控制软件Linux被控端？ - 客服中心 - Oray","url":"http://service.oray.com/question/1379.html"},{"dateAdded":1574683127906,"id":"1188","index":7,"parentId":"1144","title":"Video | 主成分分析 | 80240372X 课件 | 学堂在线","url":"http://www.xuetangx.com/courses/course-v1:TsinghuaX+80240372X+sp/courseware/5a39f1e295d8443fb4290e1cdecc9173/818ddbd077e54c4ca1b5fa2e81fa0afe/"},{"dateAdded":1574683127906,"id":"1189","index":8,"parentId":"1144","title":"jupyter中添加conda虚拟环境 - zsweety - CSDN博客","url":"https://blog.csdn.net/u014665013/article/details/81084604"},{"dateAdded":1574683127906,"id":"1190","index":9,"parentId":"1144","title":"PyCharm配置远程python解释器 - aift的专栏 - CSDN博客","url":"https://blog.csdn.net/ft_sunshine/article/details/91894221"}],"dateAdded":1574683127863,"dateGroupModified":1574683127906,"id":"1144","index":6,"parentId":"1","title":"教程"},{"children":[{"dateAdded":1574683127906,"id":"1191","index":0,"parentId":"1145","title":"MongoDB数据库安装及配置环境(windows10系统) - Tim晨 - 博客园","url":"https://www.cnblogs.com/tim100/p/6721415.html"},{"dateAdded":1574683127907,"id":"1192","index":1,"parentId":"1145","title":"Linux 平台安装 MongoDB | 菜鸟教程","url":"https://www.runoob.com/mongodb/mongodb-linux-install.html"}],"dateAdded":1574683127863,"dateGroupModified":1574683127907,"id":"1145","index":7,"parentId":"1","title":"数据库"},{"children":[{"dateAdded":1574683127907,"id":"1193","index":0,"parentId":"1146","title":"Python Extension Packages for Windows","url":"https://www.lfd.uci.edu/~gohlke/pythonlibs/"},{"dateAdded":1574683127907,"id":"1194","index":1,"parentId":"1146","title":"Ubuntu下创建虚拟独立的Python环境全过程_python_脚本之家","url":"https://www.jb51.net/article/105179.htm"},{"dateAdded":1574683127907,"id":"1195","index":2,"parentId":"1146","title":"Anaconda完全入门指南 - 简书","url":"https://www.jianshu.com/p/eaee1fadc1e9"},{"dateAdded":1574683127907,"id":"1196","index":3,"parentId":"1146","title":"Anaconda在windows安装与环境配置 - 水金的博客 - CSDN博客","url":"https://blog.csdn.net/qq_37392932/article/details/81210470"},{"dateAdded":1574683127907,"id":"1197","index":4,"parentId":"1146","title":"基于TensorFlow虚拟环境的Jupyter Notebook的使用windows - 玥晓珖的博客 - CSDN博客","url":"https://blog.csdn.net/u010327061/article/details/80303867"}],"dateAdded":1574683127864,"dateGroupModified":1574683127907,"id":"1146","index":8,"parentId":"1","title":"Python"},{"children":[{"dateAdded":1574683127907,"id":"1198","index":0,"parentId":"1147","title":"Java Algorithms and Clients","url":"https://algs4.cs.princeton.edu/code/"},{"dateAdded":1574683127908,"id":"1199","index":1,"parentId":"1147","title":"数据挖掘：理论与算法（自主模式）-学堂在线-精品中文慕课(mooc)平台","url":"http://www.xuetangx.com/courses/course-v1:TsinghuaX+80240372X+sp/about"}],"dateAdded":1574683127864,"dateGroupModified":1574683127908,"id":"1147","index":9,"parentId":"1","title":"算法"},{"children":[{"dateAdded":1574683127908,"id":"1200","index":0,"parentId":"1148","title":"PhysioNet","url":"https://physionet.org/"},{"dateAdded":1574683127908,"id":"1201","index":1,"parentId":"1148","title":"机器学习(周志华西瓜书) 参考答案 总目录 - CSDN博客","url":"https://blog.csdn.net/icefire_tyh/article/details/52064910"},{"dateAdded":1574683127908,"id":"1202","index":2,"parentId":"1148","title":"我的学习 - 网易云课堂","url":"http://study.163.com/my#/smarts"},{"dateAdded":1574683127908,"id":"1203","index":3,"parentId":"1148","title":"Mathematical optimization","url":"https://lagunita.stanford.edu/courses/Engineering/CVX101/Winter2014/courseware/7206c57866504e83821d00b5d3f80793/a87df9fb325c4bf49c3cd10a1681a6eb/"},{"dateAdded":1574683127908,"id":"1204","index":4,"parentId":"1148","title":"機器學習基石上 (Machine Learning Foundations)---Mathematical Foundations - 首页 | Coursera","url":"https://www.coursera.org/learn/ntumlone-mathematicalfoundations/home/welcome?utm_medium=email&utm_source=other&utm_campaign=opencourse.welcome.ntumlone-mathematicalfoundations.~opencourse.welcome._-SeZWb9EeWXpwqLqkqVsw."},{"dateAdded":1574683127908,"id":"1205","index":5,"parentId":"1148","title":"K-means聚类算法","url":"https://www.cnblogs.com/jerrylead/archive/2011/04/06/2006910.html?tdsourcetag=s_pctim_aiomsg"},{"dateAdded":1574683127909,"id":"1206","index":6,"parentId":"1148","title":"SpikeKing/keras-yolo3-detection: YOLO v3 目标检测算法 源码","url":"https://github.com/SpikeKing/keras-yolo3-detection"},{"dateAdded":1574683127909,"id":"1207","index":7,"parentId":"1148","title":"YOLOv2 论文笔记 ","url":"https://blog.csdn.net/jesse_mx/article/details/53925356"},{"dateAdded":1574683127909,"id":"1208","index":8,"parentId":"1148","title":"yolov3","url":"https://blog.csdn.net/qq_14845119/article/details/80335225"},{"dateAdded":1574683127909,"id":"1209","index":9,"parentId":"1148","title":"KERAS-YOLOV3的代码走读","url":"https://blog.csdn.net/yangchengtest/article/details/80664415"},{"dateAdded":1574683127909,"id":"1210","index":10,"parentId":"1148","title":"这是一个转型AI的励志故事，从非科班到拿下竞赛一等奖 - CSDN博客","url":"https://blog.csdn.net/CSDNedu/article/details/82153228"},{"dateAdded":1574683127909,"id":"1211","index":11,"parentId":"1148","title":"LightGBM算法总结 - 城市幽灵 - CSDN博客","url":"https://blog.csdn.net/weixin_39807102/article/details/81912566#12-lightgbm-%E7%9A%84%E5%8A%A8%E6%9C%BA"},{"dateAdded":1574683127909,"id":"1212","index":12,"parentId":"1148","title":"SecRepo - Security Data Samples Repository","url":"http://www.secrepo.com/"},{"dateAdded":1574683127910,"id":"1213","index":13,"parentId":"1148","title":"八大无监督异常检测技术 | D.W's Notes - Machine Learning","url":"http://www.csuldw.com/2019/03/24/2019-03-24-anomaly-detection-introduction/?from=timeline&isappinstalled=0"},{"dateAdded":1574683127910,"id":"1214","index":14,"parentId":"1148","title":"Python：SMOTE算法 - 简书","url":"https://www.jianshu.com/p/ecbc924860af"},{"dateAdded":1574683127910,"id":"1215","index":15,"parentId":"1148","title":"图卷积网络 GCN Graph Convolutional Network（谱域GCN）的理解和详细推导 - 无知人生，记录点滴 - CSDN博客","url":"https://blog.csdn.net/yyl424525/article/details/100058264#6_Graph_443"}],"dateAdded":1574683127864,"dateGroupModified":1574683127910,"id":"1148","index":10,"parentId":"1","title":"机器学习"},{"children":[{"dateAdded":1574683127910,"id":"1216","index":0,"parentId":"1149","title":"一文读懂Faster RCNN","url":"https://zhuanlan.zhihu.com/p/31426458"},{"dateAdded":1574683127910,"id":"1217","index":1,"parentId":"1149","title":"YOLO（You Only Look Once）算法详解","url":"https://blog.csdn.net/u014380165/article/details/72616238"},{"dateAdded":1574683127910,"id":"1218","index":2,"parentId":"1149","title":"目标检测|SSD原理与实现","url":"https://zhuanlan.zhihu.com/p/33544892"},{"dateAdded":1574683127911,"id":"1219","index":3,"parentId":"1149","title":"CornerNet 算法笔记","url":"https://blog.csdn.net/u014380165/article/details/83032273"},{"dateAdded":1574683127911,"id":"1220","index":4,"parentId":"1149","title":"CornerNet算法解读","url":"https://zhuanlan.zhihu.com/p/53407590"},{"dateAdded":1574683127911,"id":"1221","index":5,"parentId":"1149","title":"目标检测论文阅读：CornerNet ","url":"https://blog.csdn.net/qq_21949357/article/details/82687053"},{"dateAdded":1574683127911,"id":"1222","index":6,"parentId":"1149","title":"CenterNet算法笔记","url":"https://blog.csdn.net/u014380165/article/details/92801206"},{"dateAdded":1574683127911,"id":"1223","index":7,"parentId":"1149","title":"CenterNet :Objects as Points","url":"https://blog.csdn.net/c20081052/article/details/89358658"}],"dateAdded":1574683127865,"dateGroupModified":1574683127911,"id":"1149","index":11,"parentId":"1","title":"CV"},{"children":[{"dateAdded":1574683127912,"id":"1224","index":0,"parentId":"1150","title":"适用于PowerEdge R720的支持 | 支持主题和文章 | Dell 中国","url":"http://www.dell.com/support/home/cn/zh/cndhs1/product-support/product/poweredge-r720/research"},{"dateAdded":1574683127912,"id":"1225","index":1,"parentId":"1150","title":"在Linux上使用vim编辑文本内容 - HilaryHe - 博客园","url":"https://www.cnblogs.com/heyangyi/p/8656559.html"},{"dateAdded":1574683127912,"id":"1226","index":2,"parentId":"1150","title":"linux环境下安装nginx步骤 - 进击的乌龟 - 博客园","url":"https://www.cnblogs.com/wyd168/p/6636529.html"},{"dateAdded":1574683127913,"id":"1227","index":3,"parentId":"1150","title":"Linux平台下使用nginx与nginx-rtmp-module搭建RTMP+HLS流媒体服务器 - liuchen1206的专栏 - CSDN博客","url":"https://blog.csdn.net/liuchen1206/article/details/77771703"},{"dateAdded":1574683127913,"id":"1228","index":4,"parentId":"1150","title":"搭建nginx rtmp流媒体服务器（超详细） - 刘婶的专栏 - CSDN博客","url":"https://blog.csdn.net/szydwy/article/details/78632222"},{"dateAdded":1574683127913,"id":"1229","index":5,"parentId":"1150","title":"centos7+nginx+rtmp+ffmpeg搭建流媒体服务器 - 简书","url":"https://www.jianshu.com/p/aa7f9e204a62"},{"dateAdded":1574683127913,"id":"1230","index":6,"parentId":"1150","title":"Ubuntu 16.04 Server 版安装过程图文详解 - zhengchaooo的博客 - CSDN博客","url":"https://blog.csdn.net/zhengchaooo/article/details/79500209"},{"dateAdded":1574683127913,"id":"1231","index":7,"parentId":"1150","title":"Windows + Ubuntu 16.04 双系统安装详细教程 - flyyufenfei的博客 - CSDN博客","url":"https://blog.csdn.net/flyyufenfei/article/details/79187656"}],"dateAdded":1574683127865,"dateGroupModified":1574683127913,"id":"1150","index":12,"parentId":"1","title":"服务器"},{"children":[{"children":[{"dateAdded":1574683127918,"id":"1253","index":0,"parentId":"1232","title":"android开发百度地图点聚合功能 - 一个人的价值取决于所在位置 - CSDN博客","url":"https://blog.csdn.net/bojinyanfeng/article/details/82801437"},{"dateAdded":1574683127918,"id":"1254","index":1,"parentId":"1232","title":"细读百度地图点聚合源码（上） - javine的专栏 - CSDN博客","url":"https://blog.csdn.net/javine/article/details/51195014"},{"dateAdded":1574683127918,"id":"1255","index":2,"parentId":"1232","title":"细读百度地图点聚合源码(下)---Renderer类解析 - javine的专栏 - CSDN博客","url":"https://blog.csdn.net/javine/article/details/51234279"}],"dateAdded":1574683127914,"dateGroupModified":1574683127918,"id":"1232","index":0,"parentId":"1151","title":"百度地图"},{"dateAdded":1574683127914,"id":"1233","index":1,"parentId":"1151","title":"Android XML shape 标签使用详解（apk瘦身，减少内存好帮手） - popfisher - 博客园","url":"https://www.cnblogs.com/popfisher/p/6238119.html"},{"dateAdded":1574683127914,"id":"1234","index":2,"parentId":"1151","title":"转: Android基于HLS和RTMP协议的第三方SDK选择 - 跬步者 - 博客园","url":"https://www.cnblogs.com/jhj117/p/5598051.html"},{"dateAdded":1574683127914,"id":"1235","index":3,"parentId":"1151","title":"pili-engineering/PLDroidPlayer: PLDroidPlayer 是七牛推出的一款免费的适用于 Android 平台的播放器 SDK，采用全自研的跨平台播放内核，拥有丰富的功能和优异的性能，可高度定制化和二次开发。","url":"https://github.com/pili-engineering/PLDroidPlayer"},{"dateAdded":1574683127914,"id":"1236","index":4,"parentId":"1151","title":"Android 播放端 SDK_SDK_直播云 - 七牛开发者中心","url":"https://developer.qiniu.com/pili/sdk/1210/the-android-client-sdk"},{"dateAdded":1574683127914,"id":"1237","index":5,"parentId":"1151","title":"Android OkHttp3（完美封装）Get异步获取数据、Post异步获取数据、Form表单提交、文件下载 - 宇少095 - 博客园","url":"https://www.cnblogs.com/leichentao0905/p/6991761.html"},{"dateAdded":1574683127915,"id":"1238","index":6,"parentId":"1151","title":"Map 图标 - 1,180 个免费矢量图标下载 - Easyicon","url":"https://www.easyicon.net/iconsearch/map/?s=addtime_DESC"},{"dateAdded":1574683127915,"id":"1239","index":7,"parentId":"1151","title":"Iconfont-阿里巴巴矢量图标库","url":"http://www.iconfont.cn/home/index?spm=a313x.7781069.1998910419.2"}],"dateAdded":1574683127865,"dateGroupModified":1574683127915,"id":"1151","index":13,"parentId":"1","title":"安卓"},{"children":[{"dateAdded":1574683127915,"id":"1240","index":0,"parentId":"1152","title":"推荐系统遇上深度学习(十八)--探秘阿里之深度兴趣网络(DIN)浅析及实现 - jiangjiane - CSDN博客","url":"https://blog.csdn.net/jiangjiang_jian/article/details/80816231"}],"dateAdded":1574683127865,"dateGroupModified":1574683127915,"id":"1152","index":14,"parentId":"1","title":"推荐系统"},{"children":[{"children":[{"dateAdded":1574683127919,"id":"1256","index":0,"parentId":"1241","title":"广告曝光原理、常见问题分析与优化","url":"https://bjqq.gensee.com/webcast/site/vod/play-382dc93c47f84d30a4d87091dab1863b"},{"dateAdded":1574683127919,"id":"1257","index":1,"parentId":"1241","title":"腾讯广告算法大赛","url":"https://algo.qq.com/application/home/home/index.html"},{"dateAdded":1574683127919,"id":"1258","index":2,"parentId":"1241","title":"腾讯广告算法大赛","url":"https://mp.weixin.qq.com/s?__biz=MzIzMzgzOTUxNA==&mid=2247484010&idx=1&sn=4caae50159210837ab566bb2174be068&chksm=e8fecc9fdf894589b3cfb1bd5d01f92bf028846087403a4cdbc63ed88b03eda39a0f6fb53d5c&mpshare=1&scene=23&srcid=#rd"}],"dateAdded":1574683127915,"dateGroupModified":1574683127919,"id":"1241","index":0,"parentId":"1153","title":"腾讯"},{"children":[{"dateAdded":1574683127920,"id":"1259","index":0,"parentId":"1242","title":"天池AI学习","url":"https://tianchi.aliyun.com/course/index?spm=5176.12281976.0.0.486776d8L07yVs"},{"dateAdded":1574683127920,"id":"1260","index":1,"parentId":"1242","title":"天池大数据竞赛-天池大赛-阿里云天池","url":"https://tianchi.aliyun.com/competition/gameList/activeList"},{"dateAdded":1574683127920,"id":"1261","index":2,"parentId":"1242","title":"[印象盐城]数创未来大数据竞赛 - 乘用车零售量预测-天池大赛-阿里云天池","url":"https://tianchi.aliyun.com/competition/entrance/231640/forum"}],"dateAdded":1574683127915,"dateGroupModified":1574683127920,"id":"1242","index":1,"parentId":"1153","title":"天池"},{"children":[{"dateAdded":1574683127920,"id":"1262","index":0,"parentId":"1243","title":"2018年研究生数学建模竞赛-E题讨论区 - 数模论坛 - Powered by Discuz!","url":"http://www.shumo.com/forum/forum.php?mod=forumdisplay&fid=147"},{"dateAdded":1574683127920,"id":"1263","index":1,"parentId":"1243","title":"ECharts Demo","url":"http://echarts.baidu.com/examples/"},{"dateAdded":1574683127920,"id":"1264","index":2,"parentId":"1243","title":"VisioCafe free visio stencils download site","url":"http://www.visiocafe.com/index.htm"}],"dateAdded":1574683127915,"dateGroupModified":1574683127920,"id":"1243","index":2,"parentId":"1153","title":"数模"},{"children":[{"dateAdded":1574683127921,"id":"1265","index":0,"parentId":"1244","title":"DataFountain","url":"https://www.datafountain.cn/"},{"children":[{"dateAdded":1574683127922,"id":"1271","index":0,"parentId":"1266","title":"CCF乘用车细分市场销量预测-0.63模型框架 - 知乎","url":"https://zhuanlan.zhihu.com/p/82416104"},{"dateAdded":1574683127922,"id":"1272","index":1,"parentId":"1266","title":"CCF2019乘用车细分市场销量预测-baseline分享 - 知乎","url":"https://zhuanlan.zhihu.com/p/82738239"}],"dateAdded":1574683127921,"dateGroupModified":1574938683865,"id":"1266","index":1,"parentId":"1244","title":"乘用车"}],"dateAdded":1574683127915,"dateGroupModified":1574683127921,"id":"1244","index":3,"parentId":"1153","title":"DataFountion"},{"children":[{"dateAdded":1574683127921,"id":"1267","index":0,"parentId":"1245","title":"比赛 - Kesci.com","url":"https://www.kesci.com/home/competition"}],"dateAdded":1574683127916,"dateGroupModified":1574683127921,"id":"1245","index":4,"parentId":"1153","title":"kesci"},{"children":[{"dateAdded":1574683127921,"id":"1268","index":0,"parentId":"1246","title":"Kaggle: Your Home for Data Science","url":"https://www.kaggle.com/"}],"dateAdded":1574683127916,"dateGroupModified":1574683127921,"id":"1246","index":5,"parentId":"1153","title":"kaggle"},{"children":[{"dateAdded":1574683127921,"id":"1269","index":0,"parentId":"1247","title":"DataCastle数据城堡","url":"https://www.pkbigdata.com/"}],"dateAdded":1574683127916,"dateGroupModified":1574683127921,"id":"1247","index":6,"parentId":"1153","title":"DataCastle"},{"children":[{"dateAdded":1574683127921,"id":"1270","index":0,"parentId":"1248","title":"2019 iFLYTEK AI开发者大赛-讯飞开放平台","url":"http://challenge.xfyun.cn/2019/"}],"dateAdded":1574683127916,"dateGroupModified":1574683127921,"id":"1248","index":7,"parentId":"1153","title":"讯飞"}],"dateAdded":1574683127866,"dateGroupModified":1574683127916,"id":"1153","index":15,"parentId":"1","title":"竞赛"},{"children":[{"dateAdded":1574683127916,"id":"1249","index":0,"parentId":"1154","title":"Unsupervised Feature Learning and Deep Learning Tutorial","url":"http://ufldl.stanford.edu/tutorial/"},{"dateAdded":1574683127916,"id":"1250","index":1,"parentId":"1154","title":"各领域公开数据集下载","url":"https://zhuanlan.zhihu.com/p/25138563"},{"dateAdded":1574683127917,"id":"1251","index":2,"parentId":"1154","title":"安全数据集","url":"https://xz.aliyun.com/t/1879"},{"dateAdded":1574683127917,"id":"1252","index":3,"parentId":"1154","title":"Network Data Repository | The First Interactive Network Data Repository","url":"http://networkrepository.com/index.php"}],"dateAdded":1574683127866,"dateGroupModified":1574683127917,"id":"1154","index":16,"parentId":"1","title":"数据集"}],"dateAdded":1536245467488,"dateGroupModified":1574683127866,"id":"1","index":0,"parentId":"0","title":"书签栏"}]